[{"question": "\uac8c\uc784\uc758 \ubaa9\uc801\uc740 \ubb34\uc5c7\uc778\uac00\uc694?", "answer": "\uac8c\uc784\uc758 \ubaa9\uc801\uc740 \ube44\ud2b8, \ubcf4\uceec \ubc0f \uba5c\ub85c\ub514\ub97c \uacb0\ud569\ud558\uc5ec \uc790\uc2e0\uc758 \uc74c\uc545 \ud2b8\ub799\uc744 \ub9cc\ub4e4\uc5b4\ub0b4\ub294 \uac83\uc785\ub2c8\ub2e4."}, {"question": "Sprunki Retake\uc5d0 \uba40\ud2f0\ud50c\ub808\uc774\uc5b4 \ubaa8\ub4dc\uac00 \uc788\uc2b5\ub2c8\uae4c?", "answer": "\uc544\ub2c8\uc694, Sprunki Retake\ub294 \uc2f1\uae00\ud50c\ub808\uc774\uc5b4 \uac8c\uc784\uc785\ub2c8\ub2e4."}, {"question": "\ubaa8\ubc14\uc77c \uc7a5\uce58\uc5d0\uc11c Sprunki Retake\ub97c \uc0ac\uc6a9\ud560 \uc218 \uc788\uc2b5\ub2c8\uae4c?", "answer": "\uc608, Sprunki Retake\ub294 \ubaa8\ubc14\uc77c \uc7a5\uce58\ub97c \uc704\ud574 \ucd5c\uc801\ud654\ub418\uc5b4 \uc788\uc73c\uba70 iOS \ubc0f Android \uc7a5\uce58\uc5d0\uc11c \ud50c\ub808\uc774\ud560 \uc218 \uc788\uc2b5\ub2c8\ub2e4."}, {"question": "Sprunki Retake\uc5d0\ub294 \uc571 \ub0b4 \uad6c\ub9e4\uac00 \uc788\uc2b5\ub2c8\uae4c?", "answer": "Sprunki Retake\uc5d0\ub294 \uc571 \ub0b4 \uad6c\ub9e4\uac00 \uc5c6\uc2b5\ub2c8\ub2e4. \uac8c\uc784\uc740 \uc644\uc804\ud788 \ubb34\ub8cc\ub85c \ud50c\ub808\uc774\ud560 \uc218 \uc788\uc2b5\ub2c8\ub2e4."}, {"question": "Sprunki Retake\uc5d0\uc11c \uc0ac\uc6a9\ud560 \uc218 \uc788\ub294 \uce90\ub9ad\ud130\ub294 \uba87 \uac1c\uc785\ub2c8\uae4c?", "answer": "Sprunki Retake\uc5d0\uc11c \ucd1d 10\uac1c\uc758 \uce90\ub9ad\ud130\uac00 \uc0ac\uc6a9\ud560 \uc218 \uc788\uc73c\uba70, \uac01\uac01 \uace0\uc720\ud55c \uc18c\ub9ac\uc640 \ub2a5\ub825\uc744 \uac00\uc9c0\uace0 \uc788\uc2b5\ub2c8\ub2e4."}, {"question": "\uc18c\uc15c \ubbf8\ub514\uc5b4\uc5d0 \ub098\uc758 \uc74c\uc545 \ucc3d\uc791\ubb3c\uc744 \uacf5\uc720\ud560 \uc218 \uc788\uc2b5\ub2c8\uae4c?", "answer": "\uc608, Sprunki Retake\uc758 \ub179\uc74c \uae30\ub2a5\uc744 \uc0ac\uc6a9\ud558\uc5ec \ubbf9\uc2a4\ub97c \ucea1\uccd0\ud558\uace0 \uc18c\uc15c \ubbf8\ub514\uc5b4\uc5d0 \uacf5\uc720\ud560 \uc218 \uc788\uc2b5\ub2c8\ub2e4."}, {"question": "Sprunki Retake\uc5d0 \ud29c\ud1a0\ub9ac\uc5bc\uc774\ub098 \ub3c4\uc6c0\ub9d0 \uc139\uc158\uc774 \uc788\uc2b5\ub2c8\uae4c?", "answer": "\uc608, Sprunki Retake\uc5d0\ub294 \uac8c\uc784\uc758 \uba54\ucee4\ub2c8\uc998\uacfc \ucee8\ud2b8\ub864\uc5d0 \ub300\ud55c \uac1c\uc694\ub97c \uc81c\uacf5\ud558\ub294 \ud29c\ud1a0\ub9ac\uc5bc \uc139\uc158\uc774 \uc788\uc2b5\ub2c8\ub2e4."}, {"question": "Sprunki Retake\uac00 \uc6d0\ub798\uc758 Incredibox \uac8c\uc784\uacfc \uc5b4\ub5bb\uac8c \ub2e4\ub978\uac00\uc694?", "answer": "Sprunki Retake\ub294 \uc0c8\ub85c\uc6b4 \uc74c\uc545 \uc2a4\ud0c0\uc77c, \uce90\ub9ad\ud130 \ubc0f \uc2dc\uac01\uc801 \uc694\uc18c\ub97c \ub3c4\uc785\ud558\uc5ec \ud50c\ub808\uc774\uc5b4\uc5d0\uac8c \ud655\uc7a5\ub41c \uc74c\uc545 \ubbf9\uc2f1 \uacbd\ud5d8\uc744 \uc81c\uacf5\ud569\ub2c8\ub2e4."}]